pypanzer/tools/__init__.py
pypanzer/tools/allure_tools.py
pypanzer/tools/common_tools.py
pypanzer/tools/database_tools.py
pypanzer-1.0.4.dist-info/WHEEL
pypanzer-1.0.4.dist-info/METADATA
pypanzer-1.0.4.dist-info/RECORD
