Metadata-Version: 2.1
Name: pypanzer
Version: 1.0.4
Summary: panzer tools for python language
License: MIT
Author: 于中华
Author-email: 583512498@qq.com
Requires-Python: >=3.7.4,<4.0.0
Classifier: License :: OSI Approved :: MIT License
Classifier: Programming Language :: Python :: 3
Classifier: Programming Language :: Python :: 3.8
Classifier: Programming Language :: Python :: 3.9
Requires-Dist: SQLAlchemy (>=1.3.9,<2.0.0)
Requires-Dist: emoji (>=1.2.0,<2.0.0)
Requires-Dist: loguru (>=0.4.1,<0.5.0)
Requires-Dist: pandas (>=1.2.3,<2.0.0)
Requires-Dist: pymongo (>=3.9.0,<4.0.0)
Requires-Dist: pymysql (>=0.9.3,<0.10.0)
Requires-Dist: redis (>=3.5.3,<4.0.0)
Requires-Dist: requests (>=2.22.0,<3.0.0)
Requires-Dist: selenium (>=3.141.0,<4.0.0)
Requires-Dist: xmltodict (>=0.12.0,<0.13.0)
